LICENSE
MANIFEST.in
README.creole
setup.py
molly/__init__.py
molly/urls.py
molly.egg-info/PKG-INFO
molly.egg-info/SOURCES.txt
molly.egg-info/dependency_links.txt
molly.egg-info/requires.txt
molly.egg-info/top_level.txt
molly/apps/__init__.py
molly/apps/contact/__init__.py
molly/apps/contact/forms.py
molly/apps/contact/models.py
molly/apps/contact/urls.py
molly/apps/contact/views.py
molly/apps/contact/providers/__init__.py
molly/apps/contact/providers/mit.py
molly/apps/contact/templates/contact/base.html
molly/apps/contact/templates/contact/index.html
molly/apps/contact/templates/contact/result.html
molly/apps/contact/templates/contact/result_list.html
molly/apps/contact/templates/contact/search_form.html
molly/apps/desktop/__init__.py
molly/apps/desktop/urls.py
molly/apps/desktop/views.py
molly/apps/desktop/static/desktop/images/background.gif
molly/apps/desktop/static/desktop/images/brandmark.gif
molly/apps/desktop/static/desktop/images/eduroam.png
molly/apps/desktop/static/desktop/images/iphone.png
molly/apps/desktop/static/desktop/images/jisc-logo-small.png
molly/apps/desktop/static/desktop/images/logo.png
molly/apps/desktop/static/desktop/images/nexus-one.png
molly/apps/desktop/static/desktop/images/oucs-logo-small.png
molly/apps/desktop/static/desktop/images/phones.png
molly/apps/desktop/static/desktop/images/barcodes/datamatrix-small.png
molly/apps/desktop/static/desktop/images/barcodes/datamatrix.png
molly/apps/desktop/static/desktop/images/barcodes/facebook.png
molly/apps/desktop/static/desktop/images/barcodes/facebook.svg
molly/apps/desktop/static/desktop/images/barcodes/identica.png
molly/apps/desktop/static/desktop/images/barcodes/mstag-small.png
molly/apps/desktop/static/desktop/images/barcodes/mstag.png
molly/apps/desktop/static/desktop/images/barcodes/qrcode-small.png
molly/apps/desktop/static/desktop/images/barcodes/qrcode.png
molly/apps/desktop/static/desktop/images/barcodes/twitter.png
molly/apps/desktop/static/desktop/images/features/contact-search.png
molly/apps/desktop/static/desktop/images/features/instant-info.png
molly/apps/desktop/static/desktop/images/features/library-search-1.png
