Metadata-Version: 1.1
Name: molly
Version: 1.4.11
Summary: A framework for building mobile information portals
Home-page: http://mollyproject.org/
Author: The Molly Project
Author-email: UNKNOWN
License: Apache 2.0
Platform: UNKNOWN
Classifier: Framework :: Django
Classifier: Development Status :: 5 - Production/Stable
Classifier: License :: OSI Approved :: Apache Software License
Classifier: Intended Audience :: Education
Classifier: Operating System :: OS Independent
Classifier: Programming Language :: Python
Classifier: Topic :: Education
Classifier: Topic :: Internet
